dsc/__init__.py
dsc/gcp/__init__.py
dsc/gcp/bigquery.py
dsc/util/__init__.py
dsc/util/data.py
dsc/util/date.py
dsc/util/db.py
dsc/util/error.py
dsc/util/obj.py
dsc/util/pd.py
dsc/util/sqlalchemy.py
dsc/util/str.py
data_science_common-0.1.22.dist-info/LICENSE
data_science_common-0.1.22.dist-info/METADATA
data_science_common-0.1.22.dist-info/WHEEL
data_science_common-0.1.22.dist-info/top_level.txt
data_science_common-0.1.22.dist-info/RECORD
