Metadata-Version: 2.1
Name: data-science-common
Version: 0.1.22
Summary: UNDER CONSTRUCTION: A simple python library to facilitate analysis
Author-email: Ryan Kelley <kelleyrw@gmail.com>, Randall Kelley <randall.s.kelley@gmail.com>
License: Apache License
Project-URL: repository, https://github.com/kelleyrw/data_science_common
Project-URL: documentation, https://kelleyrw.github.io/data_science_common/docs/build/html/index.html
Keywords: data science,analysis
Classifier: Development Status :: 2 - Pre-Alpha
Classifier: Intended Audience :: Science/Research
Classifier: Topic :: Scientific/Engineering
Classifier: License :: OSI Approved :: Apache Software License
Classifier: Programming Language :: Python :: 3.7
Classifier: Programming Language :: Python :: 3.8
Classifier: Programming Language :: Python :: 3.9
Classifier: Programming Language :: Python :: 3.10
Requires-Python: >=3.7
License-File: LICENSE
Requires-Dist: sphinx
Requires-Dist: pandas
Requires-Dist: SQLAlchemy (<=2.0)
Requires-Dist: tabulate
Requires-Dist: types-tabulate
Requires-Dist: sqlparse
Requires-Dist: matplotlib
Requires-Dist: ipython
Requires-Dist: stringcase
Requires-Dist: google-cloud-bigquery
Requires-Dist: pandas-gbq
Requires-Dist: grpcio
Requires-Dist: gcsfs
Requires-Dist: pybigquery
Requires-Dist: tqdm
Requires-Dist: inflection
Provides-Extra: build
Requires-Dist: setuptools ; extra == 'build'
Requires-Dist: wheel ; extra == 'build'
Requires-Dist: twine ; extra == 'build'
Requires-Dist: build ; extra == 'build'
Requires-Dist: sphinx ; extra == 'build'
Requires-Dist: sphinx-rtd-theme ; extra == 'build'
Requires-Dist: sphinx-pyproject ; extra == 'build'
Provides-Extra: dev
Requires-Dist: black ; extra == 'dev'
Requires-Dist: flake8 ; extra == 'dev'
Requires-Dist: bumpver ; extra == 'dev'
Requires-Dist: isort ; extra == 'dev'
Requires-Dist: mypy ; extra == 'dev'
Requires-Dist: pytest ; extra == 'dev'
Requires-Dist: pip-tools ; extra == 'dev'
Requires-Dist: sphinx ; extra == 'dev'
Requires-Dist: sphinx-rtd-theme ; extra == 'dev'
Requires-Dist: python-dotenv ; extra == 'dev'
